skshift/__init__.py
skshift/audits.py
skshift/distributionshift.py
skshift-0.1.5.dist-info/METADATA
skshift-0.1.5.dist-info/WHEEL
skshift-0.1.5.dist-info/licenses/LICENSE
skshift-0.1.5.dist-info/RECORD
