Metadata-Version: 2.1
Name: skshift
Version: 0.1.5
Summary: Explanation Shift
Project-URL: Homepage, https://github.com/cmougan/skshift
Project-URL: Bug Tracker, https://github.com/cmougan/skshift/issues
Author-email: Carlos Mougan <carmougan@gmail.com>
License: MIT License
License-File: LICENSE
Classifier: License :: OSI Approved :: MIT License
Classifier: Operating System :: OS Independent
Classifier: Programming Language :: Python :: 3
Requires-Python: >=3.7
